README.md
setup.cfg
setup.py
serialio/__init__.py
serialio.egg-info/PKG-INFO
serialio.egg-info/SOURCES.txt
serialio.egg-info/dependency_links.txt
serialio.egg-info/requires.txt
serialio.egg-info/top_level.txt
serialio.egg-info/zip-safe
serialio/aio/__init__.py
serialio/aio/base.py
serialio/aio/posix.py
serialio/aio/rfc2217.py
serialio/aio/tango.py
serialio/aio/tcp.py
serialio/sio/__init__.py
serialio/sio/posix.py
serialio/sio/rfc2217.py
serialio/sio/tango.py
serialio/sio/tcp.py