Metadata-Version: 2.1
Name: serialio
Version: 2.4.0
Summary: Concurrency agnostic serialio API
Home-page: https://tiagocoutinho.github.io/serialio/
Author: Jose Tiago Macara Coutinho
Author-email: coutinhotiago@gmail.com
License: GPLv3+
Keywords: serial,rs232,rcf2217,socket,tcp,ser2net
Platform: UNKNOWN
Classifier: Development Status :: 2 - Pre-Alpha
Classifier: Intended Audience :: Developers
Classifier: Natural Language :: English
Classifier: Programming Language :: Python :: 3
Classifier: Programming Language :: Python :: 3.5
Classifier: Programming Language :: Python :: 3.6
Classifier: Programming Language :: Python :: 3.7
Classifier: Programming Language :: Python :: 3.8
Classifier: Programming Language :: Python :: 3.9
Classifier: License :: OSI Approved :: GNU General Public License v3 or later (GPLv3+)
Requires-Python: >=3.5
Provides-Extra: tango
